[{"__type__":"cc.SceneAsset","_name":"7_Finish2","scene":{"__id__":1},"asyncLoadAssets":false},{"__type__":"cc.Scene","_anchorPoint":{"__type__":"cc.Vec2"},"_children":[{"__id__":2}],"autoReleaseAssets":false},{"__type__":"cc.Node","_name":"Canvas","_parent":{"__id__":1},"_contentSize":{"__type__":"cc.Size","width":1500,"height":800},"_children":[{"__id__":3},{"__type__":"cc.Node","_name":"compoments","_parent":{"__id__":2}},{"__id__":4}],"_position":{"__type__":"cc.Vec2","x":750,"y":400},"_id":"fe955Bd8iNHArIpiJrWNAWG","_components":[{"__type__":"cc.Canvas","node":{"__id__":2},"_designResolution":{"__type__":"cc.Size","width":1500,"height":800},"_fitWidth":true}]},{"__type__":"cc.Node","_name":"bg","_parent":{"__id__":2},"_contentSize":{"__type__":"cc.Size","width":1400,"height":786},"_components":[{"__type__":"cc.Sprite","node":{"__id__":3},"_spriteFrame":{"__uuid__":"f07499c9-109a-4ca1-86a5-a1a1c37c5e06"}}]},{"__type__":"cc.Node","_name":"button","_parent":{"__id__":2},"_children":[{"__id__":5},{"__id__":6},{"__id__":7},{"__id__":8},{"__id__":9},{"__id__":10},{"__id__":11},{"__id__":12}]},{"__type__":"cc.Node","_name":"btn_next","_parent":{"__id__":4},"_contentSize":{"__type__":"cc.Size","width":81,"height":82},"_position":{"__type__":"cc.Vec2","x":570,"y":-250},"_components":[{"__type__":"cc.Sprite","node":{"__id__":5},"_spriteFrame":{"__uuid__":"479adcaf-bfd4-4c5e-9b3b-7ecc95dab012"}},{"__type__":"cc.Button","node":{"__id__":5},"transition":2,"pressedSprite":{"__uuid__":"2f598725-f5ef-4afc-88cf-7b47876318d9"},"_N$normalSprite":{"__uuid__":"479adcaf-bfd4-4c5e-9b3b-7ecc95dab012"},"_N$target":{"__id__":5}}]},{"__type__":"cc.Node","_name":"btn_return","_parent":{"__id__":4},"_contentSize":{"__type__":"cc.Size","width":82,"height":82},"_position":{"__type__":"cc.Vec2","x":-580,"y":-250},"_components":[{"__type__":"cc.Sprite","node":{"__id__":6},"_spriteFrame":{"__uuid__":"bdb8feaa-1148-43dd-ae3e-a2370d1c172d"}},{"__type__":"cc.Button","node":{"__id__":6},"transition":2,"pressedSprite":{"__uuid__":"92cd73fb-bbf3-49a3-93a7-9b33b212cb03"},"clickEvents":[{"__type__":"cc.ClickEvent","target":{"__id__":6},"component":"JumpScene","handler":"to_6_Dujin"}],"_N$normalSprite":{"__uuid__":"bdb8feaa-1148-43dd-ae3e-a2370d1c172d"},"_N$target":{"__id__":6}},{"__type__":"23652dz2JVO0oWNciLiHvGL","node":{"__id__":6}}]},{"__type__":"cc.Node","_name":"btn_toZhuye","_parent":{"__id__":4},"_contentSize":{"__type__":"cc.Size","width":82,"height":82},"_position":{"__type__":"cc.Vec2","x":-590,"y":255},"_components":[{"__type__":"cc.Sprite","node":{"__id__":7},"_spriteFrame":{"__uuid__":"68b8d574-f888-4849-95c9-870f02380822"}},{"__type__":"cc.Button","node":{"__id__":7},"transition":2,"pressedSprite":{"__uuid__":"9e018815-6dc3-42b9-82a7-2bf01bc622dd"},"clickEvents":[{"__type__":"cc.ClickEvent","target":{"__id__":7},"component":"JumpScene","handler":"to_0_Index"}],"_N$normalSprite":{"__uuid__":"68b8d574-f888-4849-95c9-870f02380822"},"_N$target":{"__id__":7}},{"__type__":"23652dz2JVO0oWNciLiHvGL","node":{"__id__":7}}]},{"__type__":"cc.Node","_name":"btn_Yinyue","_parent":{"__id__":4},"_contentSize":{"__type__":"cc.Size","width":83,"height":82},"_position":{"__type__":"cc.Vec2","x":-500,"y":255},"_components":[{"__type__":"cc.Sprite","node":{"__id__":8},"_spriteFrame":{"__uuid__":"a669ec27-8e55-41d8-92c2-2f32e6bd70e2"}},{"__type__":"cc.Button","node":{"__id__":8},"transition":2,"pressedSprite":{"__uuid__":"dc148738-b87c-4d77-a601-c19dfb7d64aa"},"_N$normalSprite":{"__uuid__":"a669ec27-8e55-41d8-92c2-2f32e6bd70e2"},"_N$target":{"__id__":8}}]},{"__type__":"cc.Node","_name":"btn_Yinxiao","_parent":{"__id__":4},"_contentSize":{"__type__":"cc.Size","width":82,"height":82},"_position":{"__type__":"cc.Vec2","x":-410,"y":255},"_components":[{"__type__":"cc.Sprite","node":{"__id__":9},"_spriteFrame":{"__uuid__":"99703960-be2e-4ec8-ac4f-ee3e64353f15"}},{"__type__":"cc.Button","node":{"__id__":9},"transition":2,"pressedSprite":{"__uuid__":"9e4e2229-7a9a-472f-91a6-5da285efccf5"},"_N$normalSprite":{"__uuid__":"99703960-be2e-4ec8-ac4f-ee3e64353f15"},"_N$target":{"__id__":9}}]},{"__type__":"cc.Node","_name":"btn_box2","_parent":{"__id__":4},"_contentSize":{"__type__":"cc.Size","width":248,"height":162},"_components":[{"__type__":"cc.Sprite","node":{"__id__":10},"_spriteFrame":{"__uuid__":"8bb2e05f-165d-4884-bad9-487397a45f90"}},{"__type__":"cc.Button","node":{"__id__":10},"transition":2,"pressedSprite":{"__uuid__":"3c7c273d-7dfc-43dc-b1fe-8283e47036c4"},"hoverSprite":{"__uuid__":"975e1c32-d3b2-4c4e-9261-5621cc350c05"},"clickEvents":[{"__type__":"cc.ClickEvent","target":{"__id__":10},"component":"JumpScene2","handler":"to_0_Xuanze2"}],"_N$normalSprite":{"__uuid__":"8bb2e05f-165d-4884-bad9-487397a45f90"},"_N$target":{"__id__":10}},{"__type__":"d5d59RW1XpNe7YcRO9uYB+E","node":{"__id__":10}}]},{"__type__":"cc.Node","_name":"btn_box3","_parent":{"__id__":4},"_contentSize":{"__type__":"cc.Size","width":248,"height":162},"_position":{"__type__":"cc.Vec2","x":300},"_components":[{"__type__":"cc.Sprite","node":{"__id__":11},"_spriteFrame":{"__uuid__":"8bb2e05f-165d-4884-bad9-487397a45f90"}},{"__type__":"cc.Button","node":{"__id__":11},"transition":2,"pressedSprite":{"__uuid__":"86887e23-751c-4b27-a4f6-7bc563da6620"},"hoverSprite":{"__uuid__":"975e1c32-d3b2-4c4e-9261-5621cc350c05"},"clickEvents":[{"__type__":"cc.ClickEvent","target":{"__id__":11},"component":"JumpScene2","handler":"to_0_Xuanze2"}],"_N$normalSprite":{"__uuid__":"8bb2e05f-165d-4884-bad9-487397a45f90"},"_N$target":{"__id__":11}},{"__type__":"d5d59RW1XpNe7YcRO9uYB+E","node":{"__id__":11}}]},{"__type__":"cc.Node","_name":"btn_box1","_parent":{"__id__":4},"_contentSize":{"__type__":"cc.Size","width":248,"height":162},"_position":{"__type__":"cc.Vec2","x":-300},"_components":[{"__type__":"cc.Sprite","node":{"__id__":12},"_spriteFrame":{"__uuid__":"8bb2e05f-165d-4884-bad9-487397a45f90"}},{"__type__":"cc.Button","node":{"__id__":12},"transition":2,"pressedSprite":{"__uuid__":"119ffe46-52a9-4cee-801c-d9a7bd24c4e9"},"hoverSprite":{"__uuid__":"975e1c32-d3b2-4c4e-9261-5621cc350c05"},"clickEvents":[{"__type__":"cc.ClickEvent","target":{"__id__":12},"component":"JumpScene","handler":"to_8_GameOver"}],"_N$normalSprite":{"__uuid__":"8bb2e05f-165d-4884-bad9-487397a45f90"},"_N$target":{"__id__":12}},{"__type__":"23652dz2JVO0oWNciLiHvGL","node":{"__id__":12}}]}]